{
  "同步时间": "2026-05-16",
  "来源": "猎手主系统",
  "同步类型": "持仓数据",
  "同步版本": "v6.05",
  "说明": "3只防御股持仓数据，需与龙虾持仓.json比对",
  "持仓": [
    {
      "代码": "600377",
      "名称": "宁沪高速",
      "股数": 1000,
      "成本": 12.345,
      "现价": 12.26,
      "止损": 11.80,
      "止盈": 13.00,
      "预警": "🟢安全",
      "类型": "防御",
      "备注": "收费公路，现金流稳定，防御属性强"
    },
    {
      "代码": "600795",
      "名称": "国电电力",
      "股数": 2000,
      "成本": 4.903,
      "现价": 4.92,
      "止损": 4.65,
      "止盈": 5.20,
      "预警": "🟢安全",
      "类型": "防御",
      "备注": "电力主升浪催化持续，12家机构买入评级，目标价6.11元(+24%)"
    },
    {
      "代码": "600089",
      "名称": "特变电工",
      "股数": 100,
      "成本": 27.552,
      "现价": 26.92,
      "止损": 26.50,
      "止盈": 29.00,
      "预警": "🔴危险",
      "类型": "防御",
      "备注": "主力3日净流出24.57亿，短期承压；机构目标价31.42元(+17%)"
    }
  ],
  "仓位汇总": {
    "总仓位": "38%",
    "防御仓": "38%",
    "进攻仓": "0%",
    "现金": "62%",
    "现金金额": 39090
  },
  "灯色": "🟡黄灯",
  "环境评分": 52
}
